txTwitter-0.1.6.dist-info/DESCRIPTION.rst
txTwitter-0.1.6.dist-info/METADATA
txTwitter-0.1.6.dist-info/RECORD
txTwitter-0.1.6.dist-info/WHEEL
txTwitter-0.1.6.dist-info/metadata.json
txTwitter-0.1.6.dist-info/top_level.txt
txtwitter/__init__.py
txtwitter/error.py
txtwitter/messagetools.py
txtwitter/streamservice.py
txtwitter/twitter.py
txtwitter/tests/__init__.py
txtwitter/tests/fake_agent.py
txtwitter/tests/fake_twitter.py
txtwitter/tests/test_do_not_commit.py
txtwitter/tests/test_fake_agent.py
txtwitter/tests/test_fake_twitter.py
txtwitter/tests/test_messagetools.py
txtwitter/tests/test_streamservice.py
txtwitter/tests/test_twitter.py
