Metadata-Version: 2.0
Name: txTwitter
Version: 0.1.6
Summary: A Twisted-based client library for Twitter's API.
Home-page: https://github.com/jerith/txTwitter
Author: Jeremy Thurgood
Author-email: firxen@gmail.com
License: MIT
Platform: UNKNOWN
Classifier: Development Status :: 3 - Alpha
Classifier: Framework :: Twisted
Classifier: Intended Audience :: Developers
Classifier: License :: OSI Approved :: MIT License
Classifier: Programming Language :: Python
Classifier: Topic :: Software Development :: Libraries :: Python Modules
Requires-Dist: Twisted (>=13.1.0)
Requires-Dist: oauthlib
Requires-Dist: pyOpenSSL
